haven/__init__.py
haven/api.py
haven/choice.py
haven/component.py
haven/decoding.py
haven/encoding.py
haven/formats.py
haven/includer.py
haven/type_inspector.py
haven/type_registry.py
haven/types.py
haven/utils.py
haven_conf-0.1.0.dist-info/entry_points.txt
haven_conf-0.1.0.dist-info/LICENSE
haven_conf-0.1.0.dist-info/WHEEL
haven_conf-0.1.0.dist-info/METADATA
haven_conf-0.1.0.dist-info/RECORD
