Metadata-Version: 2.1
Name: haven-conf
Version: 0.1.0
Summary: Simple and flexible dataclass configuration system
Author-email: Jon Morton <jon@jamorton.com>
Requires-Python: >=3.10.1
Classifier: Development Status :: 3 - Alpha
Classifier: Intended Audience :: Developers
Classifier: License :: OSI Approved :: MIT License
Classifier: Programming Language :: Python :: 3 :: Only
Classifier: Programming Language :: Python :: 3.10
Classifier: Programming Language :: Python :: 3.11
Classifier: Programming Language :: Python :: 3.12
Requires-Dist: fsspec
Requires-Dist: flit >=3.2.0,<4.0.0 ; extra == "dev"
Requires-Dist: ruff ; extra == "dev"
Requires-Dist: sphinx >=5.1.1,<9.0.0 ; extra == "doc"
Requires-Dist: sphinx-rtd-theme ; extra == "doc"
Requires-Dist: bandit[toml] ; extra == "test"
Requires-Dist: check-manifest ; extra == "test"
Requires-Dist: pre-commit ; extra == "test"
Requires-Dist: pytest-cov ; extra == "test"
Requires-Dist: pytest-mock ; extra == "test"
Requires-Dist: pytest-runner ; extra == "test"
Requires-Dist: pytest ; extra == "test"
Requires-Dist: pytest-github-actions-annotate-failures ; extra == "test"
Requires-Dist: shellcheck-py ; extra == "test"
Project-URL: Documentation, https://github.com/jonmorton/haven/tree/main#readme
Project-URL: Issues, https://github.com/jonmorton/haven/issues
Project-URL: Source, https://github.com/jonmorton/haven
Provides-Extra: dev
Provides-Extra: doc
Provides-Extra: test
